setup.py
delnone/__init__.py
delnone.egg-info/PKG-INFO
delnone.egg-info/SOURCES.txt
delnone.egg-info/dependency_links.txt
delnone.egg-info/not-zip-safe
delnone.egg-info/top_level.txt