Metadata-Version: 1.0
Name: delnone
Version: 0.3
Summary: Function which removes "None"s from data structures.
Home-page: https://github.com/andrewguy9/delnone
Author: andrew thomson
Author-email: athomsonguy@gmail.com
License: MIT
Platform: UNKNOWN
